PyFQL/__init__.py
PyFQL/database.py
PyFQL/pattern.py
PyFQL/query_builder.py
PyFQL/execption/__init__.py
PyFQL/execption/custom_execption.py
PyFQL-0.0.2.dist-info/LICENSE
PyFQL-0.0.2.dist-info/METADATA
PyFQL-0.0.2.dist-info/WHEEL
PyFQL-0.0.2.dist-info/top_level.txt
PyFQL-0.0.2.dist-info/RECORD
