Metadata-Version: 2.1
Name: PyFQL
Version: 0.0.2
Home-page: https://github.com/yannbanas/PyFQL
Author: Banas Yann
Author-email: yannbanas@gmail.com
Classifier: Development Status :: 2 - Pre-Alpha
Classifier: Intended Audience :: Developers
Classifier: License :: OSI Approved :: MIT License
Classifier: Programming Language :: Python :: 3.9
License-File: LICENSE
